[{"link": "http://lettingfees.co.uk/update-2017#how-have-fees-changed", "name": "How have fees changed?", "children": []}, {"link": "http://lettingfees.co.uk/update-2017#arla-research", "name": "ARLA Research", "children": []}, {"link": "http://lettingfees.co.uk/update-2017#distorting-effects", "name": "Distorting Effects", "children": []}, {"link": "http://lettingfees.co.uk/update-2017#exceptions", "name": "Exceptions", "children": []}, {"link": "http://lettingfees.co.uk/update-2017#a-better-lettings-market", "name": "A Better Lettings Market", "children": []}]